Metadata-Version: 2.1
Name: orangearg
Version: 0.1.2
Summary: Argument mining and reasoning add-on on Orange3 platform.
Home-page: https://github.com/EyeofBeholder-NLeSC/orange3-argument
Author: Ji Qi
Project-URL: Bug Tracker, https://github.com/EyeofBeholder-NLeSC/orange3-argument/issues
Classifier: Development Status :: 3 - Alpha
Classifier: Intended Audience :: Developers
Classifier: License :: OSI Approved :: Apache Software License
Classifier: Natural Language :: English
Classifier: Programming Language :: Python :: 3
Classifier: Programming Language :: Python :: 3.8
Classifier: Programming Language :: Python :: 3.9
Classifier: Programming Language :: Python :: 3.10
Classifier: Programming Language :: Python :: 3.11
Requires-Python: >=3.8
License-File: LICENSE
Requires-Dist: orange3
Requires-Dist: pyqt6
Requires-Dist: pyqt6-webengine
Requires-Dist: sip
Requires-Dist: numpy <=1.24
Requires-Dist: textblob
Requires-Dist: spacy
Requires-Dist: bertopic
Requires-Dist: networkx
Requires-Dist: scikit-learn
Provides-Extra: dev
Requires-Dist: prospector[with_pyroma] ; extra == 'dev'
Requires-Dist: pytest ; extra == 'dev'
Requires-Dist: pytest-mock ; extra == 'dev'
Requires-Dist: pytest-cov ; extra == 'dev'
Requires-Dist: sphinx ; extra == 'dev'
Requires-Dist: sphinx-rtd-theme ; extra == 'dev'
Requires-Dist: sphinx-autoapi ; extra == 'dev'
Requires-Dist: myst-parser ; extra == 'dev'
Requires-Dist: nbsphinx ; extra == 'dev'
Requires-Dist: nbsphinx-link ; extra == 'dev'
Requires-Dist: black ; extra == 'dev'
Requires-Dist: pylint ; extra == 'dev'
Provides-Extra: publishing
Requires-Dist: twine ; extra == 'publishing'
Requires-Dist: wheel ; extra == 'publishing'
